mensajes/__init__.py
mensajes/adios/__init__.py
mensajes/adios/despido.py
mensajes/hola/__init__.py
mensajes/hola/saludos.py
test/__init__.py
test/test_hola.py
Mensajes_jrivera-9.0.dist-info/LICENSE
Mensajes_jrivera-9.0.dist-info/METADATA
Mensajes_jrivera-9.0.dist-info/WHEEL
Mensajes_jrivera-9.0.dist-info/top_level.txt
Mensajes_jrivera-9.0.dist-info/RECORD
