Metadata-Version: 2.1
Name: Mensajes-jrivera
Version: 9.0
Summary: Un paquete para saludar y despedir 
Home-page: https://www.colocarrepositoriogithub.pe
Author: Jaime Rivera Chávez 
Author-email: jrivera@oceansandrivers.pe
Classifier: Environment :: Console
Classifier: Intended Audience :: Developers
Classifier: License :: OSI Approved :: MIT License
Classifier: Operating System :: OS Independent
Classifier: Programming Language :: Python
Classifier: Programming Language :: Python :: 3.11
Classifier: Topic :: Utilities
License-File: LICENSE
Requires-Dist: numpy >=1.26.3
